c4dynamics/__init__.py
c4dynamics/datasets/__init__.py
c4dynamics/datasets/_manager.py
c4dynamics/datasets/_registry.py
c4dynamics/detectors/__init__.py
c4dynamics/detectors/yolo3_opencv.py
c4dynamics/envs/__init__.py
c4dynamics/envs/mountain_car.py
c4dynamics/eqm/__init__.py
c4dynamics/eqm/derivs.py
c4dynamics/eqm/integrate.py
c4dynamics/filters/__init__.py
c4dynamics/filters/ekf.py
c4dynamics/filters/kalman.py
c4dynamics/filters/lowpass.py
c4dynamics/rotmat/__init__.py
c4dynamics/rotmat/animate.py
c4dynamics/rotmat/rotmat.py
c4dynamics/sensors/__init__.py
c4dynamics/sensors/lineofsight.py
c4dynamics/sensors/radar.py
c4dynamics/sensors/seeker.py
c4dynamics/states/__init__.py
c4dynamics/states/state.py
c4dynamics/states/lib/__init__.py
c4dynamics/states/lib/datapoint.py
c4dynamics/states/lib/pixelpoint.py
c4dynamics/states/lib/rigidbody.py
c4dynamics/utils/__init__.py
c4dynamics/utils/_struct.py
c4dynamics/utils/const.py
c4dynamics/utils/cprint.py
c4dynamics/utils/gen_gif.py
c4dynamics/utils/idx2keys.py
c4dynamics/utils/images_loader.py
c4dynamics/utils/math.py
c4dynamics/utils/plottools.py
c4dynamics/utils/plottracks.py
c4dynamics/utils/printpts.py
c4dynamics/utils/slides_gen.py
c4dynamics/utils/tictoc.py
c4dynamics/utils/video_gen.py
c4dynamics/utils/vidgen.py
c4dynamics-2.3.3.dist-info/licenses/LICENSE
c4dynamics-2.3.3.dist-info/METADATA
c4dynamics-2.3.3.dist-info/WHEEL
c4dynamics-2.3.3.dist-info/top_level.txt
c4dynamics-2.3.3.dist-info/RECORD
