Metadata-Version: 2.4
Name: c4dynamics
Version: 2.3.3
Summary: Python framework for state-space modeling and algorithm development
Author: c4dynamics
Author-email: Ziv Meri <zivmeri@gmail.com>
License-Expression: MIT
Keywords: python,state-space,dynamics,physics,algorithms,computer vision,navigation,guidance,slam,vslam,image processing,signal processing,control
Classifier: Development Status :: 5 - Production/Stable
Classifier: Intended Audience :: Developers
Classifier: Programming Language :: Python :: 3
Classifier: Operating System :: Unix
Classifier: Operating System :: MacOS :: MacOS X
Classifier: Operating System :: Microsoft :: Windows
Requires-Python: >=3.8,<3.13
License-File: LICENSE
Requires-Dist: imageio>=2.37.0
Requires-Dist: matplotlib>=3.9.2
Requires-Dist: natsort>=8.3.1
Requires-Dist: numpy>=1.26.0
Requires-Dist: opencv-python>=4.11.0.86
Requires-Dist: pooch>=1.8.0
Requires-Dist: scipy>=1.13.0
Provides-Extra: dev
Requires-Dist: nbsphinx>=0.9.3; extra == "dev"
Requires-Dist: Sphinx>=8.1.3; extra == "dev"
Requires-Dist: sphinx-book-theme>=1.1.4; extra == "dev"
Requires-Dist: sphinx_design>=0.6.1; extra == "dev"
Dynamic: author
Dynamic: license-file
Dynamic: requires-python
